README
setup.cfg
setup.py
summa/__init__.py
summa/commons.py
summa/graph.py
summa/keywords.py
summa/pagerank_weighted.py
summa/summarizer.py
summa/syntactic_unit.py
summa/textrank.py
summa.egg-info/PKG-INFO
summa.egg-info/SOURCES.txt
summa.egg-info/dependency_links.txt
summa.egg-info/entry_points.txt
summa.egg-info/requires.txt
summa.egg-info/top_level.txt
summa/exception/__init__.py
summa/exception/textrank_runtime_error.py
summa/preprocessing/__init__.py
summa/preprocessing/porter.py
summa/preprocessing/snowball.py
summa/preprocessing/stopwords.py
summa/preprocessing/textcleaner.py
test/test_keywords.py
test/test_summarizer.py