Metadata-Version: 1.2
Name: summa
Version: 1.0.0
Summary: A text summarization and keyword extraction package based on TextRank
Home-page: https://github.com/summanlp/textrank
Author: Federico Barrios, Federico Lopez
Author-email: UNKNOWN
License: UNKNOWN
Download-URL: https://github.com/summanlp/textrank/tarball/v1.0.0
Keywords: summa,nlp,summarization,NLP,natural language processing,automatic summarization,keywords,summary,textrank,pagerank
Platform: UNKNOWN
Classifier: Development Status :: 5 - Production/Stable
Classifier: License :: OSI Approved :: MIT License
Classifier: Intended Audience :: Developers
Classifier: Intended Audience :: Education
Classifier: Topic :: Scientific/Engineering :: Information Analysis
Classifier: Topic :: Text Processing :: Linguistic
Classifier: Programming Language :: Python :: 3 :: Only
Requires-Python: >=3.4
